setup.py
syncstomp/__init__.py
syncstomp/args.py
syncstomp/cli.py
syncstomp/conversation.py
syncstomp/json_wrap.py
syncstomp/managed.py
syncstomp/patch.py
syncstomp/rpc.py
syncstomp.egg-info/PKG-INFO
syncstomp.egg-info/SOURCES.txt
syncstomp.egg-info/dependency_links.txt
syncstomp.egg-info/entry_points.txt
syncstomp.egg-info/requires.txt
syncstomp.egg-info/top_level.txt