Metadata-Version: 1.0
Name: syncstomp
Version: 0.3
Summary: Synchronous STOMP library with automatic provider discovery
Home-page: http://github.com/LuminosoInsight/syncstomp
Author: Luminoso, LLC
Author-email: dev@lumino.so
License: MIT
Platform: any
